stabilityai/__init__.py
stabilityai/client.py
stabilityai/constants.py
stabilityai/exceptions.py
stabilityai/models.py
stabilityai/utils.py
stabilityai-1.0.5.dist-info/LICENSE
stabilityai-1.0.5.dist-info/METADATA
stabilityai-1.0.5.dist-info/WHEEL
stabilityai-1.0.5.dist-info/top_level.txt
stabilityai-1.0.5.dist-info/RECORD
