Metadata-Version: 2.1
Name: stabilityai
Version: 1.0.5
Summary: *Unofficial* client for the Stability REST API
Author-email: Estelle Poulin <dev@inspiredby.es>
License: GPLv3
Project-URL: homepage, https://github.com/estheruary/stabilityai
Project-URL: repository, https://github.com/estheruary/stabilityai
Project-URL: changelog, https://github.com/estheruary/stabilityai/-/blob/main/CHANGELOG.md
Keywords: stabilityai,bot
Classifier: Programming Language :: Python :: 3
Requires-Python: >=3.11
License-File: LICENSE
Requires-Dist: aiohttp ==3.8.4
Requires-Dist: pydantic[email] ==1.10.2
